tulflow/__init__.py
tulflow/_version.py
tulflow/harvest.py
tulflow/process.py
tulflow/solr_api_utils.py
tulflow/tasks.py
tulflow/transform.py
tulflow/validate.py
tulflow-0.12.14.dist-info/METADATA
tulflow-0.12.14.dist-info/WHEEL
tulflow-0.12.14.dist-info/top_level.txt
tulflow-0.12.14.dist-info/RECORD
