Metadata-Version: 2.4
Name: tulflow
Version: 0.12.14
Summary: Package of Temple University Library Indexing & ETL functions used by Airflow.
Author-email: Temple University Libraries <tuh42082@temple.edu>
License: Apache License (2.0)
Project-URL: homepage, https://github.com/tulibraries/tulflow
Classifier: Programming Language :: Python :: 3
Classifier: Operating System :: OS Independent
Requires-Dist: nose
